{
  "name": "My workflow",
  "nodes": [
    {
      "parameters": {
        "pollTimes": {
          "item": [
            {
              "mode": "everyMinute"
            }
          ]
        },
        "simple": false,
        "filters": {
          "labelIds": [
            "INBOX"
          ],
          "q": "Subject: Daily Sales"
        },
        "options": {
          "downloadAttachments": true
        }
      },
      "type": "n8n-nodes-base.gmailTrigger",
      "typeVersion": 1.2,
      "position": [
        0,
        0
      ],
      "id": "5958e88f-2924-4a8b-af68-de008c82f706",
      "name": "Gmail Trigger",
      "credentials": {
        "gmailOAuth2": {
          "id": "lZ7izNXrj1ntzO2q",
          "name": "Gmail account"
        }
      }
    },
    {
      "parameters": {
        "schema": {
          "__rl": true,
          "mode": "list",
          "value": "public"
        },
        "table": {
          "__rl": true,
          "value": "fact_order_line",
          "mode": "list",
          "cachedResultName": "fact_order_line"
        },
        "columns": {
          "mappingMode": "defineBelow",
          "value": {
            "order_id": "={{ $json.order_id }}",
            "order_placement_date": "={{ $json.order_placement_date.toDateTime(\"dd-MM-yyyy\").format('yyyy-MM-dd') }}",
            "customer_id": "={{ $json.customer_id }}",
            "product_id": "={{ $json.product_id }}",
            "order_qty": "={{ $json.order_qty }}",
            "delivery_qty": "={{ $json.delivery_qty }}",
            "agreed_delivery_date": "={{ $json.agreed_delivery_date.toDateTime(\"dd-MM-yyyy\").format('yyyy-MM-dd') }}",
            "actual_delivery_date": "={{ $json.actual_delivery_date.toDateTime(\"dd-MM-yyyy\").format('yyyy-MM-dd') }}",
            "In Full": "={{ $json['In Full'] }}",
            "On Time": "={{ $json['On Time'] }}",
            "On Time In Full": "={{ $json['On Time In Full'] }}"
          },
          "matchingColumns": [],
          "schema": [
            {
              "id": "order_id",
              "displayName": "order_id",
              "required": false,
              "defaultMatch": false,
              "display": true,
              "type": "string",
              "canBeUsedToMatch": true
            },
            {
              "id": "order_placement_date",
              "displayName": "order_placement_date",
              "required": false,
              "defaultMatch": false,
              "display": true,
              "type": "dateTime",
              "canBeUsedToMatch": true
            },
            {
              "id": "customer_id",
              "displayName": "customer_id",
              "required": false,
              "defaultMatch": false,
              "display": true,
              "type": "number",
              "canBeUsedToMatch": true
            },
            {
              "id": "product_id",
              "displayName": "product_id",
              "required": false,
              "defaultMatch": false,
              "display": true,
              "type": "number",
              "canBeUsedToMatch": true,
              "removed": false
            },
            {
              "id": "order_qty",
              "displayName": "order_qty",
              "required": false,
              "defaultMatch": false,
              "display": true,
              "type": "number",
              "canBeUsedToMatch": true,
              "removed": false
            },
            {
              "id": "agreed_delivery_date",
              "displayName": "agreed_delivery_date",
              "required": false,
              "defaultMatch": false,
              "display": true,
              "type": "dateTime",
              "canBeUsedToMatch": true,
              "removed": false
            },
            {
              "id": "actual_delivery_date",
              "displayName": "actual_delivery_date",
              "required": false,
              "defaultMatch": false,
              "display": true,
              "type": "dateTime",
              "canBeUsedToMatch": true,
              "removed": false
            },
            {
              "id": "delivery_qty",
              "displayName": "delivery_qty",
              "required": false,
              "defaultMatch": false,
              "display": true,
              "type": "number",
              "canBeUsedToMatch": true,
              "removed": false
            },
            {
              "id": "In Full",
              "displayName": "In Full",
              "required": false,
              "defaultMatch": false,
              "display": true,
              "type": "string",
              "canBeUsedToMatch": true,
              "removed": false
            },
            {
              "id": "On Time",
              "displayName": "On Time",
              "required": false,
              "defaultMatch": false,
              "display": true,
              "type": "string",
              "canBeUsedToMatch": true,
              "removed": false
            },
            {
              "id": "On Time In Full",
              "displayName": "On Time In Full",
              "required": false,
              "defaultMatch": false,
              "display": true,
              "type": "string",
              "canBeUsedToMatch": true,
              "removed": false
            }
          ],
          "attemptToConvertTypes": false,
          "convertFieldsToString": false
        },
        "options": {}
      },
      "type": "n8n-nodes-base.postgres",
      "typeVersion": 2.6,
      "position": [
        416,
        0
      ],
      "id": "0f9a71c3-5db6-495b-952c-a05a3de56ab5",
      "name": "Insert rows in a table",
      "credentials": {
        "postgres": {
          "id": "iRrhvuL5qradWsk3",
          "name": "Postgres account"
        }
      }
    },
    {
      "parameters": {
        "binaryPropertyName": "attachment_0",
        "options": {}
      },
      "type": "n8n-nodes-base.extractFromFile",
      "typeVersion": 1,
      "position": [
        208,
        0
      ],
      "id": "aca93cd8-1c3e-4c28-bc88-c5ae247a04ce",
      "name": "Extract from File: OrderLine"
    },
    {
      "parameters": {
        "binaryPropertyName": "attachment_1",
        "options": {}
      },
      "type": "n8n-nodes-base.extractFromFile",
      "typeVersion": 1,
      "position": [
        208,
        256
      ],
      "id": "6d9ac0f6-d7c8-49e5-8618-d2d6672a3d51",
      "name": "Extract from File: Aggregate"
    },
    {
      "parameters": {
        "schema": {
          "__rl": true,
          "mode": "list",
          "value": "public"
        },
        "table": {
          "__rl": true,
          "value": "fact_aggregate",
          "mode": "list",
          "cachedResultName": "fact_aggregate"
        },
        "columns": {
          "mappingMode": "defineBelow",
          "value": {
            "order_id": "={{ $json.order_id }}",
            "customer_id": "={{ $json.customer_id }}",
            "order_placement_date": "={{ $json.order_placement_date.toDateTime(\"dd-MM-yyyy\").format('yyyy-MM-dd') }}",
            "on_time": "={{ $json.on_time }}",
            "otif": "={{ $json.otif }}",
            "in_full": "={{ $json.in_full }}"
          },
          "matchingColumns": [],
          "schema": [
            {
              "id": "order_id",
              "displayName": "order_id",
              "required": true,
              "defaultMatch": false,
              "display": true,
              "type": "string",
              "canBeUsedToMatch": true
            },
            {
              "id": "customer_id",
              "displayName": "customer_id",
              "required": false,
              "defaultMatch": false,
              "display": true,
              "type": "number",
              "canBeUsedToMatch": true
            },
            {
              "id": "order_placement_date",
              "displayName": "order_placement_date",
              "required": false,
              "defaultMatch": false,
              "display": true,
              "type": "dateTime",
              "canBeUsedToMatch": true
            },
            {
              "id": "on_time",
              "displayName": "on_time",
              "required": false,
              "defaultMatch": false,
              "display": true,
              "type": "number",
              "canBeUsedToMatch": true
            },
            {
              "id": "in_full",
              "displayName": "in_full",
              "required": false,
              "defaultMatch": false,
              "display": true,
              "type": "string",
              "canBeUsedToMatch": true
            },
            {
              "id": "otif",
              "displayName": "otif",
              "required": false,
              "defaultMatch": false,
              "display": true,
              "type": "string",
              "canBeUsedToMatch": true
            }
          ],
          "attemptToConvertTypes": false,
          "convertFieldsToString": false
        },
        "options": {}
      },
      "type": "n8n-nodes-base.postgres",
      "typeVersion": 2.6,
      "position": [
        416,
        256
      ],
      "id": "f9d1f0e2-7c7b-4dc6-bd9b-de063b0221ce",
      "name": "Insert rows in a table1",
      "credentials": {
        "postgres": {
          "id": "iRrhvuL5qradWsk3",
          "name": "Postgres account"
        }
      }
    }
  ],
  "pinData": {},
  "connections": {
    "Gmail Trigger": {
      "main": [
        [
          {
            "node": "Extract from File: OrderLine",
            "type": "main",
            "index": 0
          },
          {
            "node": "Extract from File: Aggregate",
            "type": "main",
            "index": 0
          }
        ]
      ]
    },
    "Extract from File: OrderLine": {
      "main": [
        [
          {
            "node": "Insert rows in a table",
            "type": "main",
            "index": 0
          }
        ]
      ]
    },
    "Extract from File: Aggregate": {
      "main": [
        [
          {
            "node": "Insert rows in a table1",
            "type": "main",
            "index": 0
          }
        ]
      ]
    }
  },
  "active": false,
  "settings": {
    "executionOrder": "v1"
  },
  "versionId": "580f7542-2ae3-4b8e-af44-e9e5a6f4234c",
  "meta": {
    "templateCredsSetupCompleted": true,
    "instanceId": "029a743fee640504566fbe5df8d389ac89c3810072850520eedc066e4d509bcd"
  },
  "id": "0qLF4KNQvEWScwAJ",
  "tags": []
}